sb_final/__init__.py
sb_final/sb.py
sb_final/parsers/__init__.py
sb_final/parsers/python/__init__.py
sb_final/parsers/python/parser.py
sb_final/src/__init__.py
sb_final/src/deploy_features.py
sb_final/src/extract_features.py
sb_final/utils/__init__.py
sb_final/utils/deploy.py
sb_final/utils/django_app_dependencies.py
sb_final/utils/django_utils.py
sb_final/utils/extract.py
sb_final/utils/feature_dependencies.py
sb_final/utils/installDependencies.py
sb_final/utils/manage_url.py
sb_final/utils/package_utils.py
sb_final/utils/utils.py
sb_final/utils/var_utils.py
sb_final/utils/venv_utils.py
sb_final/utils/write_dependency.py
sb_final-0.1.dist-info/METADATA
sb_final-0.1.dist-info/WHEEL
sb_final-0.1.dist-info/entry_points.txt
sb_final-0.1.dist-info/top_level.txt
sb_final-0.1.dist-info/RECORD
