Metadata-Version: 2.4
Name: sb_final
Version: 0.1
Requires-Dist: django
Dynamic: requires-dist
